CHANGES.txt
LICENSE.txt
MANIFEST.in
README.rst
setup.cfg
setup.py
docs/build/html/_sources/index.txt
docs/build/html/_sources/common/index.txt
docs/build/html/_sources/common/timeseries.txt
docs/build/html/_sources/errors/baseerrormeasure.txt
docs/build/html/_sources/errors/customerrormeasure.txt
docs/build/html/_sources/errors/geometricmeanabsolutepercentageerror.txt
docs/build/html/_sources/errors/index.txt
docs/build/html/_sources/errors/meanabsolutedeviationerror.txt
docs/build/html/_sources/errors/meanabsolutepercentageerror.txt
docs/build/html/_sources/errors/meansquarederror.txt
docs/build/html/_sources/errors/medianabsolutepercentageerror.txt
docs/build/html/_sources/errors/symmetricmeanabsolutepercentageerror.txt
docs/build/html/_sources/methods/basemethods.txt
docs/build/html/_sources/methods/custommethods.txt
docs/build/html/_sources/methods/forecastingmethods.txt
docs/build/html/_sources/methods/index.txt
docs/build/html/_sources/methods/smoothingmethods.txt
docs/build/html/_sources/misc/pycast-conventions.txt
docs/build/html/_sources/misc/pycast-performance-optimization.txt
docs/build/html/_sources/optimization/index.txt
pycast/__init__.py
pycast.egg-info/PKG-INFO
pycast.egg-info/SOURCES.txt
pycast.egg-info/dependency_links.txt
pycast.egg-info/top_level.txt
pycast/common/__init__.py
pycast/common/decorators.py
pycast/common/helper.py
pycast/common/json_encoder.py
pycast/common/matrix.py
pycast/common/profileme.py
pycast/common/pycastobject.py
pycast/common/timeseries.py
pycast/errors/__init__.py
pycast/errors/baseerrormeasure.py
pycast/errors/geometricmeanabsolutepercentageerror.py
pycast/errors/meanabsolutedeviationerror.py
pycast/errors/meanabsolutepercentageerror.py
pycast/errors/meanabsolutescalederror.py
pycast/errors/meansigneddifferenceerror.py
pycast/errors/meansignedpercentageerror.py
pycast/errors/meansquarederror.py
pycast/errors/medianabsolutepercentageerror.py
pycast/errors/symmetricmeanabsolutepercentageerror.py
pycast/errors/weightedmeanabsolutepercentageerror.py
pycast/methods/__init__.py
pycast/methods/basemethod.py
