Metadata-Version: 1.1
Name: pycast
Version: v0.1.5-alpha
Summary: A Forecasting and Smoothing Library
Home-page: https://github.com/T-002/pycast
Author: Christian Schwarz
Author-email: christianschw4rz@gmail.com
License: UNKNOWN
Download-URL: https://github.com/T-002/pycast.git
Platform: UNKNOWN
Classifier: Development Status :: 3 - Alpha
Classifier: Intended Audience :: Education
Classifier: Intended Audience :: Science/Research
Classifier: License :: OSI Approved :: MIT License
Classifier: Topic :: Database
Classifier: Topic :: Education
Classifier: Topic :: Scientific/Engineering :: Mathematics
Classifier: Topic :: Scientific/Engineering :: Information Analysis
